configaroo/__init__.py
configaroo/configuration.py
configaroo/exceptions.py
configaroo/py.typed
configaroo/loaders/__init__.py
configaroo/loaders/json.py
configaroo/loaders/toml.py
configaroo-0.6.1.dist-info/licenses/LICENSE
configaroo-0.6.1.dist-info/METADATA
configaroo-0.6.1.dist-info/WHEEL
configaroo-0.6.1.dist-info/top_level.txt
configaroo-0.6.1.dist-info/RECORD
