Metadata-Version: 2.4
Name: configaroo
Version: 0.6.1
Summary: Bouncy handling of configuration files
Author-email: Geir Arne Hjelle <geirarne@gmail.com>
Maintainer-email: Geir Arne Hjelle <geirarne@gmail.com>
License-Expression: MIT
Project-URL: homepage, https://github.com/gahjelle/configaroo
Project-URL: github, https://github.com/gahjelle/configaroo
Project-URL: issues, https://github.com/gahjelle/configaroo/issues
Project-URL: changelog, https://github.com/gahjelle/configaroo/releases
Keywords: configuration,configuration-management,toml,json
Classifier: Development Status :: 5 - Production/Stable
Classifier: Intended Audience :: Developers
Classifier: Natural Language :: English
Classifier: Operating System :: OS Independent
Classifier: Programming Language :: Python :: 3.11
Classifier: Programming Language :: Python :: 3.12
Classifier: Programming Language :: Python :: 3.13
Classifier: Programming Language :: Python :: 3
Classifier: Topic :: Software Development :: Libraries :: Python Modules
Classifier: Typing :: Typed
Requires-Python: >=3.11
License-File: LICENSE
Requires-Dist: pydantic>=2.0
Requires-Dist: pyplugs>=0.5.4
Dynamic: license-file
